simplecmd
