Metadata-Version: 1.0
Name: simplecmd
Version: 1.0.0
Summary: Simple wrapper around subprocess
Home-page: https://github.com/nicholasbishop/simplecmd
Author: Nicholas Bishop
Author-email: nicholasbishop@gmail.com
License: Apache-2.0
Platform: UNKNOWN
